{
  "type": "FeatureCollection",
  "features": [
    {
      "type": "Feature",
      "geometry": {
        "type": "LineString",
        "coordinates": [
          [
            13.46962,
            52.50313
          ],
          [
            13.46919,
            52.50228
          ],
          [
            13.46783,
            52.49894
          ],
          [
            13.46766,
            52.4986
          ],
          [
            13.46737,
            52.49819
          ],
          [
            13.4671,
            52.49788
          ],
          [
            13.46679,
            52.49759
          ],
          [
            13.46654,
            52.49738
          ],
          [
            13.46543,
            52.49658
          ],
          [
            13.46469,
            52.49598
          ],
          [
            13.46314,
            52.49476
          ],
          [
            13.46257,
            52.49425
          ],
          [
            13.46127,
            52.49296
          ],
          [
            13.46108,
            52.49273
          ],
          [
            13.46069,
            52.49215
          ],
          [
            13.46045,
            52.49175
          ],
          [
            13.46025,
            52.49136
          ],
          [
            13.4601,
            52.49094
          ],
          [
            13.4597,
            52.4892
          ],
          [
            13.45965,
            52.48859
          ],
          [
            13.45972,
            52.48811
          ],
          [
            13.45991,
            52.48758
          ],
          [
            13.46,
            52.48742
          ],
          [
            13.4603,
            52.48699
          ],
          [
            13.46054,
            52.48673
          ],
          [
            13.46081,
            52.48647
          ],
          [
            13.46144,
            52.486
          ],
          [
            13.46531,
            52.48365
          ],
          [
            13.46741,
            52.48231
          ],
          [
            13.47142,
            52.47956
          ],
          [
            13.473,
            52.47846
          ],
          [
            13.48102,
            52.47295
          ],
          [
            13.48495,
            52.4703
          ],
          [
            13.48742,
            52.46872
          ],
          [
            13.48878,
            52.46788
          ],
          [
            13.49261,
            52.46533
          ],
          [
            13.49333,
            52.46486
          ],
          [
            13.49409,
            52.46443
          ],
          [
            13.49564,
            52.46362
          ],
          [
            13.49646,
            52.46316
          ],
          [
            13.49785,
            52.46231
          ],
          [
            13.5046,
            52.45793
          ],
          [
            13.50825,
            52.45543
          ],
          [
            13.51523,
            52.4509
          ],
          [
            13.51577,
            52.45057
          ],
          [
            13.51639,
            52.45025
          ],
          [
            13.51961,
            52.44878
          ],
          [
            13.52191,
            52.44769
          ],
          [
            13.52233,
            52.44748
          ],
          [
            13.52292,
            52.44715
          ],
          [
            13.52547,
            52.44563
          ],
          [
            13.53572,
            52.43865
          ],
          [
            13.5375,
            52.43722
          ],
          [
            13.53808,
            52.4368
          ],
          [
            13.5395,
            52.43592
          ],
          [
            13.54113,
            52.4348
          ],
          [
            13.54447,
            52.43236
          ],
          [
            13.54628,
            52.43111
          ],
          [
            13.55132,
            52.42775
          ],
          [
            13.55398,
            52.42607
          ],
          [
            13.55456,
            52.42567
          ],
          [
            13.55517,
            52.42523
          ],
          [
            13.55573,
            52.4247
          ],
          [
            13.55615,
            52.42415
          ],
          [
            13.55641,
            52.42365
          ],
          [
            13.55652,
            52.42336
          ],
          [
            13.55659,
            52.42302
          ],
          [
            13.55663,
            52.42268
          ],
          [
            13.55666,
            52.41962
          ],
          [
            13.55661,
            52.41908
          ],
          [
            13.55651,
            52.41868
          ],
          [
            13.55637,
            52.41832
          ],
          [
            13.55615,
            52.41791
          ],
          [
            13.55554,
            52.41706
          ],
          [
            13.55343,
            52.41463
          ],
          [
            13.55243,
            52.41342
          ],
          [
            13.5514,
            52.41224
          ],
          [
            13.55029,
            52.41111
          ],
          [
            13.54977,
            52.41061
          ],
          [
            13.54842,
            52.40944
          ],
          [
            13.54754,
            52.40874
          ],
          [
            13.54667,
            52.4081
          ],
          [
            13.54576,
            52.40746
          ],
          [
            13.54395,
            52.40629
          ],
          [
            13.54245,
            52.40545
          ],
          [
            13.54092,
            52.40464
          ],
          [
            13.53935,
            52.40389
          ],
          [
            13.52831,
            52.39873
          ],
          [
            13.52615,
            52.39772
          ],
          [
            13.52424,
            52.39687
          ],
          [
            13.52328,
            52.39643
          ],
          [
            13.50847,
            52.38949
          ],
          [
            13.50275,
            52.38682
          ],
          [
            13.5003,
            52.38572
          ],
          [
            13.45511,
            52.36575
          ],
          [
            13.45112,
            52.36387
          ],
          [
            13.44758,
            52.36233
          ],
          [
            13.44403,
            52.36073
          ],
          [
            13.43726,
            52.35773
          ],
          [
            13.43559,
            52.35704
          ],
          [
            13.43379,
            52.35637
          ],
          [
            13.43262,
            52.35597
          ],
          [
            13.43091,
            52.35543
          ],
          [
            13.4296,
            52.35506
          ],
          [
            13.42174,
            52.35305
          ],
          [
            13.41948,
            52.35244
          ],
          [
            13.41801,
            52.35201
          ],
          [
            13.41722,
            52.35173
          ],
          [
            13.41661,
            52.35148
          ],
          [
            13.41596,
            52.35115
          ],
          [
            13.41528,
            52.35072
          ],
          [
            13.41491,
            52.35045
          ],
          [
            13.41457,
            52.35016
          ],
          [
            13.41408,
            52.34965
          ],
          [
            13.41386,
            52.34937
          ],
          [
            13.4136,
            52.34896
          ],
          [
            13.41333,
            52.34837
          ],
          [
            13.41318,
            52.34783
          ],
          [
            13.41313,
            52.34732
          ],
          [
            13.41315,
            52.34694
          ],
          [
            13.41319,
            52.34669
          ],
          [
            13.41329,
            52.34626
          ],
          [
            13.41343,
            52.34579
          ],
          [
            13.41419,
            52.34359
          ],
          [
            13.41472,
            52.34137
          ],
          [
            13.41486,
            52.3409
          ],
          [
            13.41787,
            52.33217
          ],
          [
            13.41806,
            52.33141
          ],
          [
            13.42298,
            52.31703
          ],
          [
            13.42449,
            52.31256
          ],
          [
            13.4249,
            52.31141
          ],
          [
            13.43607,
            52.27863
          ],
          [
            13.43635,
            52.2777
          ],
          [
            13.43651,
            52.27695
          ],
          [
            13.43657,
            52.27657
          ],
          [
            13.43665,
            52.27569
          ],
          [
            13.43667,
            52.27512
          ],
          [
            13.43657,
            52.25581
          ],
          [
            13.43654,
            52.2542
          ],
          [
            13.43656,
            52.25291
          ],
          [
            13.43653,
            52.25113
          ],
          [
            13.43658,
            52.24918
          ],
          [
            13.43707,
            52.2416
          ],
          [
            13.43728,
            52.23886
          ],
          [
            13.43916,
            52.21163
          ],
          [
            13.43923,
            52.21092
          ],
          [
            13.43941,
            52.21003
          ],
          [
            13.4396,
            52.20939
          ],
          [
            13.43984,
            52.20872
          ],
          [
            13.44001,
            52.20834
          ],
          [
            13.44037,
            52.20765
          ],
          [
            13.44069,
            52.2071
          ],
          [
            13.46286,
            52.17345
          ],
          [
            13.46995,
            52.16262
          ],
          [
            13.47525,
            52.15449
          ],
          [
            13.47596,
            52.15337
          ],
          [
            13.4767,
            52.15199
          ],
          [
            13.47715,
            52.151
          ],
          [
            13.47762,
            52.14975
          ],
          [
            13.47784,
            52.14906
          ],
          [
            13.478,
            52.14844
          ],
          [
            13.47824,
            52.14738
          ],
          [
            13.4808,
            52.13159
          ],
          [
            13.48097,
            52.13085
          ],
          [
            13.4813,
            52.12961
          ],
          [
            13.48167,
            52.12848
          ],
          [
            13.48203,
            52.12753
          ],
          [
            13.48243,
            52.12658
          ],
          [
            13.50433,
            52.07775
          ],
          [
            13.50492,
            52.07631
          ],
          [
            13.51405,
            52.05231
          ],
          [
            13.51449,
            52.05132
          ],
          [
            13.51521,
            52.04998
          ],
          [
            13.51591,
            52.04886
          ],
          [
            13.51655,
            52.04795
          ],
          [
            13.51736,
            52.04692
          ],
          [
            13.51777,
            52.04642
          ],
          [
            13.51897,
            52.04511
          ],
          [
            13.53079,
            52.03257
          ],
          [
            13.53235,
            52.03106
          ],
          [
            13.53374,
            52.02983
          ],
          [
            13.54845,
            52.01719
          ],
          [
            13.54925,
            52.01648
          ],
          [
            13.54994,
            52.01581
          ],
          [
            13.55078,
            52.01486
          ],
          [
            13.5515,
            52.01392
          ],
          [
            13.55253,
            52.01239
          ],
          [
            13.56289,
            51.99654
          ],
          [
            13.56327,
            51.99588
          ],
          [
            13.56382,
            51.99489
          ],
          [
            13.58605,
            51.95254
          ],
          [
            13.58812,
            51.94854
          ],
          [
            13.58865,
            51.94742
          ],
          [
            13.58898,
            51.94654
          ],
          [
            13.58925,
            51.94566
          ],
          [
            13.58934,
            51.94526
          ],
          [
            13.5895,
            51.94438
          ],
          [
            13.58957,
            51.94373
          ],
          [
            13.58961,
            51.94262
          ],
          [
            13.58956,
            51.94177
          ],
          [
            13.58949,
            51.94125
          ],
          [
            13.58932,
            51.94035
          ],
          [
            13.58902,
            51.93929
          ],
          [
            13.5792,
            51.90884
          ],
          [
            13.57847,
            51.90653
          ],
          [
            13.57833,
            51.90594
          ],
          [
            13.57816,
            51.90488
          ],
          [
            13.57811,
            51.90425
          ],
          [
            13.57809,
            51.90362
          ],
          [
            13.57814,
            51.90265
          ],
          [
            13.57821,
            51.90201
          ],
          [
            13.57833,
            51.90135
          ],
          [
            13.57848,
            51.9007
          ],
          [
            13.57866,
            51.90008
          ],
          [
            13.57894,
            51.89932
          ],
          [
            13.57925,
            51.89859
          ],
          [
            13.57956,
            51.89799
          ],
          [
            13.58001,
            51.89722
          ],
          [
            13.61337,
            51.84291
          ],
          [
            13.61425,
            51.84152
          ],
          [
            13.61489,
            51.84066
          ],
          [
            13.6155,
            51.83994
          ],
          [
            13.61605,
            51.83936
          ],
          [
            13.61665,
            51.83877
          ],
          [
            13.61743,
            51.83807
          ],
          [
            13.63071,
            51.82673
          ],
          [
            13.63161,
            51.8259
          ],
          [
            13.63229,
            51.82517
          ],
          [
            13.63274,
            51.82457
          ],
          [
            13.63307,
            51.82406
          ],
          [
            13.63333,
            51.82355
          ],
          [
            13.63356,
            51.82299
          ],
          [
            13.63372,
            51.82247
          ],
          [
            13.6338,
            51.8221
          ],
          [
            13.63387,
            51.82159
          ],
          [
            13.6339,
            51.82117
          ],
          [
            13.63385,
            51.82038
          ],
          [
            13.63372,
            51.81965
          ],
          [
            13.6335,
            51.81897
          ],
          [
            13.63321,
            51.81833
          ],
          [
            13.63305,
            51.81804
          ],
          [
            13.63278,
            51.81761
          ],
          [
            13.63241,
            51.81709
          ],
          [
            13.63197,
            51.8166
          ],
          [
            13.63166,
            51.81628
          ],
          [
            13.63076,
            51.81548
          ],
          [
            13.62819,
            51.81348
          ],
          [
            13.62742,
            51.81286
          ],
          [
            13.62706,
            51.81254
          ],
          [
            13.62652,
            51.81202
          ],
          [
            13.6262,
            51.81168
          ],
          [
            13.62581,
            51.81123
          ],
          [
            13.62536,
            51.81061
          ],
          [
            13.62516,
            51.8103
          ],
          [
            13.62487,
            51.80972
          ],
          [
            13.62472,
            51.8094
          ],
          [
            13.62459,
            51.80905
          ],
          [
            13.62441,
            51.8084
          ],
          [
            13.62432,
            51.80784
          ],
          [
            13.62429,
            51.80749
          ],
          [
            13.62428,
            51.80709
          ],
          [
            13.62434,
            51.80621
          ],
          [
            13.62537,
            51.79971
          ],
          [
            13.62549,
            51.79853
          ],
          [
            13.62549,
            51.79758
          ],
          [
            13.62542,
            51.79673
          ],
          [
            13.62528,
            51.79584
          ],
          [
            13.62511,
            51.7951
          ],
          [
            13.62468,
            51.79376
          ],
          [
            13.61587,
            51.76923
          ],
          [
            13.61559,
            51.76838
          ],
          [
            13.59513,
            51.69763
          ],
          [
            13.59482,
            51.69664
          ],
          [
            13.58499,
            51.66814
          ],
          [
            13.58442,
            51.66654
          ],
          [
            13.58436,
            51.66631
          ],
          [
            13.57666,
            51.64403
          ],
          [
            13.57638,
            51.64332
          ],
          [
            13.57607,
            51.64267
          ],
          [
            13.57586,
            51.64227
          ],
          [
            13.57533,
            51.64137
          ],
          [
            13.57499,
            51.64088
          ],
          [
            13.57413,
            51.63974
          ],
          [
            13.56807,
            51.63206
          ],
          [
            13.5676,
            51.63139
          ],
          [
            13.56718,
            51.63068
          ],
          [
            13.56675,
            51.62978
          ],
          [
            13.56659,
            51.62937
          ],
          [
            13.56624,
            51.62831
          ],
          [
            13.5659,
            51.62715
          ],
          [
            13.56426,
            51.62085
          ],
          [
            13.56411,
            51.6203
          ],
          [
            13.56314,
            51.61654
          ],
          [
            13.56288,
            51.61528
          ],
          [
            13.5628,
            51.61451
          ],
          [
            13.56277,
            51.61402
          ],
          [
            13.56279,
            51.61291
          ],
          [
            13.56288,
            51.61212
          ],
          [
            13.56309,
            51.61099
          ],
          [
            13.56366,
            51.60907
          ],
          [
            13.56751,
            51.59669
          ],
          [
            13.56852,
            51.59321
          ],
          [
            13.57332,
            51.5765
          ],
          [
            13.57352,
            51.57568
          ],
          [
            13.57366,
            51.57484
          ],
          [
            13.57373,
            51.57417
          ],
          [
            13.5759,
            51.54606
          ],
          [
            13.57601,
            51.54428
          ],
          [
            13.57603,
            51.54238
          ],
          [
            13.5762,
            51.50925
          ],
          [
            13.57629,
            51.50427
          ],
          [
            13.57627,
            51.50343
          ],
          [
            13.57624,
            51.50306
          ],
          [
            13.57619,
            51.50262
          ],
          [
            13.57601,
            51.50182
          ],
          [
            13.57577,
            51.50112
          ],
          [
            13.57553,
            51.50058
          ],
          [
            13.57522,
            51.5
          ],
          [
            13.57469,
            51.4992
          ],
          [
            13.57432,
            51.49873
          ],
          [
            13.57371,
            51.49806
          ],
          [
            13.57307,
            51.49746
          ],
          [
            13.57244,
            51.49694
          ],
          [
            13.57182,
            51.49649
          ],
          [
            13.57131,
            51.49616
          ],
          [
            13.57032,
            51.49558
          ],
          [
            13.56572,
            51.49321
          ],
          [
            13.56481,
            51.49271
          ],
          [
            13.56306,
            51.49163
          ],
          [
            13.55101,
            51.48395
          ],
          [
            13.5499,
            51.48328
          ],
          [
            13.54908,
            51.48282
          ],
          [
            13.54835,
            51.48245
          ],
          [
            13.54739,
            51.48199
          ],
          [
            13.54679,
            51.48173
          ],
          [
            13.54533,
            51.48114
          ],
          [
            13.54381,
            51.4806
          ],
          [
            13.54326,
            51.48042
          ],
          [
            13.53003,
            51.47643
          ],
          [
            13.52841,
            51.47591
          ],
          [
            13.5274,
            51.47553
          ],
          [
            13.52693,
            51.47534
          ],
          [
            13.52597,
            51.47489
          ],
          [
            13.52522,
            51.4745
          ],
          [
            13.52458,
            51.47413
          ],
          [
            13.52386,
            51.47367
          ],
          [
            13.5235,
            51.47342
          ],
          [
            13.52316,
            51.47316
          ],
          [
            13.52237,
            51.4725
          ],
          [
            13.52193,
            51.47209
          ],
          [
            13.52163,
            51.47177
          ],
          [
            13.5211,
            51.47117
          ],
          [
            13.52088,
            51.47089
          ],
          [
            13.52054,
            51.47041
          ],
          [
            13.52014,
            51.46975
          ],
          [
            13.51978,
            51.46902
          ],
          [
            13.51949,
            51.4683
          ],
          [
            13.51632,
            51.45941
          ],
          [
            13.516513,
            51.460071
          ]
        ]
      },
      "properties": {
        "id": 6440441,
        "body": "",
        "bodyMentions": [],
        "business": 0,
        "visibility": 0,
        "likes": 4,
        "liked": false,
        "isLikable": false,
        "client": null,
        "createdAt": "2025-11-29T11:55:06+00:00",
        "train": {
          "trip": 6251264,
          "hafasId": "20251129_10:21_de-DELFI_3026478318",
          "category": "regionalExp",
          "mode": "LONG_DISTANCE",
          "number": "IC 2177",
          "lineName": "IC 2177",
          "routeColor": null,
          "journeyNumber": 2177,
          "manualJourneyNumber": null,
          "distance": 129270,
          "points": 21,
          "duration": 62,
          "manualDeparture": null,
          "manualArrival": null,
          "origin": {
            "id": 24,
            "name": "Berlin Ostkreuz",
            "rilIdentifier": "BOKS\t",
            "evaIdentifier": 8089028,
            "arrival": "2025-11-29T11:32:00+00:00",
            "arrivalPlanned": "2025-11-29T11:31:00+00:00",
            "arrivalReal": "2025-11-29T11:32:00+00:00",
            "arrivalPlatformPlanned": "13",
            "arrivalPlatformReal": "13",
            "departure": "2025-11-29T11:34:00+00:00",
            "departurePlanned": "2025-11-29T11:33:00+00:00",
            "departureReal": "2025-11-29T11:34:00+00:00",
            "departurePlatformPlanned": "13",
            "departurePlatformReal": "13",
            "platform": "13",
            "isArrivalDelayed": true,
            "isDepartureDelayed": true,
            "cancelled": false
          },
          "destination": {
            "id": 6809,
            "name": "Elsterwerda",
            "rilIdentifier": "BEW",
            "evaIdentifier": 8010099,
            "arrival": "2025-11-29T12:36:00+00:00",
            "arrivalPlanned": "2025-11-29T12:35:00+00:00",
            "arrivalReal": "2025-11-29T12:36:00+00:00",
            "arrivalPlatformPlanned": "3",
            "arrivalPlatformReal": "3",
            "departure": "2025-11-29T12:38:00+00:00",
            "departurePlanned": "2025-11-29T12:37:00+00:00",
            "departureReal": "2025-11-29T12:38:00+00:00",
            "departurePlatformPlanned": "3",
            "departurePlatformReal": "3",
            "platform": "3",
            "isArrivalDelayed": true,
            "isDepartureDelayed": true,
            "cancelled": false
          },
          "operator": {
            "id": 2747,
            "identifier": "db-fernverkehr-ag",
            "name": "DB Fernverkehr"
          },
          "dataSource": {
            "id": "9ea6b4f6-fa55-4aae-acf5-188ac9684189",
            "attribution": "Die Daten werden von transitous bereitgestellt und sind von DELFI e.V. unter der Lizenz Creative Commons Attribution 4.0 International (CC BY 4.0) lizenziert."
          },
          "polyline": {
            "type": "FeatureCollection",
            "features": [
              {
                "type": "Feature",
                "geometry": {
                  "type": "LineString",
                  "coordinates": [
                    [
                      13.46962,
                      52.50313
                    ],
                    [
                      13.46919,
                      52.50228
                    ],
                    [
                      13.46783,
                      52.49894
                    ],
                    [
                      13.46766,
                      52.4986
                    ],
                    [
                      13.46737,
                      52.49819
                    ],
                    [
                      13.4671,
                      52.49788
                    ],
                    [
                      13.46679,
                      52.49759
                    ],
                    [
                      13.46654,
                      52.49738
                    ],
                    [
                      13.46543,
                      52.49658
                    ],
                    [
                      13.46469,
                      52.49598
                    ],
                    [
                      13.46314,
                      52.49476
                    ],
                    [
                      13.46257,
                      52.49425
                    ],
                    [
                      13.46127,
                      52.49296
                    ],
                    [
                      13.46108,
                      52.49273
                    ],
                    [
                      13.46069,
                      52.49215
                    ],
                    [
                      13.46045,
                      52.49175
                    ],
                    [
                      13.46025,
                      52.49136
                    ],
                    [
                      13.4601,
                      52.49094
                    ],
                    [
                      13.4597,
                      52.4892
                    ],
                    [
                      13.45965,
                      52.48859
                    ],
                    [
                      13.45972,
                      52.48811
                    ],
                    [
                      13.45991,
                      52.48758
                    ],
                    [
                      13.46,
                      52.48742
                    ],
                    [
                      13.4603,
                      52.48699
                    ],
                    [
                      13.46054,
                      52.48673
                    ],
                    [
                      13.46081,
                      52.48647
                    ],
                    [
                      13.46144,
                      52.486
                    ],
                    [
                      13.46531,
                      52.48365
                    ],
                    [
                      13.46741,
                      52.48231
                    ],
                    [
                      13.47142,
                      52.47956
                    ],
                    [
                      13.473,
                      52.47846
                    ],
                    [
                      13.48102,
                      52.47295
                    ],
                    [
                      13.48495,
                      52.4703
                    ],
                    [
                      13.48742,
                      52.46872
                    ],
                    [
                      13.48878,
                      52.46788
                    ],
                    [
                      13.49261,
                      52.46533
                    ],
                    [
                      13.49333,
                      52.46486
                    ],
                    [
                      13.49409,
                      52.46443
                    ],
                    [
                      13.49564,
                      52.46362
                    ],
                    [
                      13.49646,
                      52.46316
                    ],
                    [
                      13.49785,
                      52.46231
                    ],
                    [
                      13.5046,
                      52.45793
                    ],
                    [
                      13.50825,
                      52.45543
                    ],
                    [
                      13.51523,
                      52.4509
                    ],
                    [
                      13.51577,
                      52.45057
                    ],
                    [
                      13.51639,
                      52.45025
                    ],
                    [
                      13.51961,
                      52.44878
                    ],
                    [
                      13.52191,
                      52.44769
                    ],
                    [
                      13.52233,
                      52.44748
                    ],
                    [
                      13.52292,
                      52.44715
                    ],
                    [
                      13.52547,
                      52.44563
                    ],
                    [
                      13.53572,
                      52.43865
                    ],
                    [
                      13.5375,
                      52.43722
                    ],
                    [
                      13.53808,
                      52.4368
                    ],
                    [
                      13.5395,
                      52.43592
                    ],
                    [
                      13.54113,
                      52.4348
                    ],
                    [
                      13.54447,
                      52.43236
                    ],
                    [
                      13.54628,
                      52.43111
                    ],
                    [
                      13.55132,
                      52.42775
                    ],
                    [
                      13.55398,
                      52.42607
                    ],
                    [
                      13.55456,
                      52.42567
                    ],
                    [
                      13.55517,
                      52.42523
                    ],
                    [
                      13.55573,
                      52.4247
                    ],
                    [
                      13.55615,
                      52.42415
                    ],
                    [
                      13.55641,
                      52.42365
                    ],
                    [
                      13.55652,
                      52.42336
                    ],
                    [
                      13.55659,
                      52.42302
                    ],
                    [
                      13.55663,
                      52.42268
                    ],
                    [
                      13.55666,
                      52.41962
                    ],
                    [
                      13.55661,
                      52.41908
                    ],
                    [
                      13.55651,
                      52.41868
                    ],
                    [
                      13.55637,
                      52.41832
                    ],
                    [
                      13.55615,
                      52.41791
                    ],
                    [
                      13.55554,
                      52.41706
                    ],
                    [
                      13.55343,
                      52.41463
                    ],
                    [
                      13.55243,
                      52.41342
                    ],
                    [
                      13.5514,
                      52.41224
                    ],
                    [
                      13.55029,
                      52.41111
                    ],
                    [
                      13.54977,
                      52.41061
                    ],
                    [
                      13.54842,
                      52.40944
                    ],
                    [
                      13.54754,
                      52.40874
                    ],
                    [
                      13.54667,
                      52.4081
                    ],
                    [
                      13.54576,
                      52.40746
                    ],
                    [
                      13.54395,
                      52.40629
                    ],
                    [
                      13.54245,
                      52.40545
                    ],
                    [
                      13.54092,
                      52.40464
                    ],
                    [
                      13.53935,
                      52.40389
                    ],
                    [
                      13.52831,
                      52.39873
                    ],
                    [
                      13.52615,
                      52.39772
                    ],
                    [
                      13.52424,
                      52.39687
                    ],
                    [
                      13.52328,
                      52.39643
                    ],
                    [
                      13.50847,
                      52.38949
                    ],
                    [
                      13.50275,
                      52.38682
                    ],
                    [
                      13.5003,
                      52.38572
                    ],
                    [
                      13.45511,
                      52.36575
                    ],
                    [
                      13.45112,
                      52.36387
                    ],
                    [
                      13.44758,
                      52.36233
                    ],
                    [
                      13.44403,
                      52.36073
                    ],
                    [
                      13.43726,
                      52.35773
                    ],
                    [
                      13.43559,
                      52.35704
                    ],
                    [
                      13.43379,
                      52.35637
                    ],
                    [
                      13.43262,
                      52.35597
                    ],
                    [
                      13.43091,
                      52.35543
                    ],
                    [
                      13.4296,
                      52.35506
                    ],
                    [
                      13.42174,
                      52.35305
                    ],
                    [
                      13.41948,
                      52.35244
                    ],
                    [
                      13.41801,
                      52.35201
                    ],
                    [
                      13.41722,
                      52.35173
                    ],
                    [
                      13.41661,
                      52.35148
                    ],
                    [
                      13.41596,
                      52.35115
                    ],
                    [
                      13.41528,
                      52.35072
                    ],
                    [
                      13.41491,
                      52.35045
                    ],
                    [
                      13.41457,
                      52.35016
                    ],
                    [
                      13.41408,
                      52.34965
                    ],
                    [
                      13.41386,
                      52.34937
                    ],
                    [
                      13.4136,
                      52.34896
                    ],
                    [
                      13.41333,
                      52.34837
                    ],
                    [
                      13.41318,
                      52.34783
                    ],
                    [
                      13.41313,
                      52.34732
                    ],
                    [
                      13.41315,
                      52.34694
                    ],
                    [
                      13.41319,
                      52.34669
                    ],
                    [
                      13.41329,
                      52.34626
                    ],
                    [
                      13.41343,
                      52.34579
                    ],
                    [
                      13.41419,
                      52.34359
                    ],
                    [
                      13.41472,
                      52.34137
                    ],
                    [
                      13.41486,
                      52.3409
                    ],
                    [
                      13.41787,
                      52.33217
                    ],
                    [
                      13.41806,
                      52.33141
                    ],
                    [
                      13.42298,
                      52.31703
                    ],
                    [
                      13.42449,
                      52.31256
                    ],
                    [
                      13.4249,
                      52.31141
                    ],
                    [
                      13.43607,
                      52.27863
                    ],
                    [
                      13.43635,
                      52.2777
                    ],
                    [
                      13.43651,
                      52.27695
                    ],
                    [
                      13.43657,
                      52.27657
                    ],
                    [
                      13.43665,
                      52.27569
                    ],
                    [
                      13.43667,
                      52.27512
                    ],
                    [
                      13.43657,
                      52.25581
                    ],
                    [
                      13.43654,
                      52.2542
                    ],
                    [
                      13.43656,
                      52.25291
                    ],
                    [
                      13.43653,
                      52.25113
                    ],
                    [
                      13.43658,
                      52.24918
                    ],
                    [
                      13.43707,
                      52.2416
                    ],
                    [
                      13.43728,
                      52.23886
                    ],
                    [
                      13.43916,
                      52.21163
                    ],
                    [
                      13.43923,
                      52.21092
                    ],
                    [
                      13.43941,
                      52.21003
                    ],
                    [
                      13.4396,
                      52.20939
                    ],
                    [
                      13.43984,
                      52.20872
                    ],
                    [
                      13.44001,
                      52.20834
                    ],
                    [
                      13.44037,
                      52.20765
                    ],
                    [
                      13.44069,
                      52.2071
                    ],
                    [
                      13.46286,
                      52.17345
                    ],
                    [
                      13.46995,
                      52.16262
                    ],
                    [
                      13.47525,
                      52.15449
                    ],
                    [
                      13.47596,
                      52.15337
                    ],
                    [
                      13.4767,
                      52.15199
                    ],
                    [
                      13.47715,
                      52.151
                    ],
                    [
                      13.47762,
                      52.14975
                    ],
                    [
                      13.47784,
                      52.14906
                    ],
                    [
                      13.478,
                      52.14844
                    ],
                    [
                      13.47824,
                      52.14738
                    ],
                    [
                      13.4808,
                      52.13159
                    ],
                    [
                      13.48097,
                      52.13085
                    ],
                    [
                      13.4813,
                      52.12961
                    ],
                    [
                      13.48167,
                      52.12848
                    ],
                    [
                      13.48203,
                      52.12753
                    ],
                    [
                      13.48243,
                      52.12658
                    ],
                    [
                      13.50433,
                      52.07775
                    ],
                    [
                      13.50492,
                      52.07631
                    ],
                    [
                      13.51405,
                      52.05231
                    ],
                    [
                      13.51449,
                      52.05132
                    ],
                    [
                      13.51521,
                      52.04998
                    ],
                    [
                      13.51591,
                      52.04886
                    ],
                    [
                      13.51655,
                      52.04795
                    ],
                    [
                      13.51736,
                      52.04692
                    ],
                    [
                      13.51777,
                      52.04642
                    ],
                    [
                      13.51897,
                      52.04511
                    ],
                    [
                      13.53079,
                      52.03257
                    ],
                    [
                      13.53235,
                      52.03106
                    ],
                    [
                      13.53374,
                      52.02983
                    ],
                    [
                      13.54845,
                      52.01719
                    ],
                    [
                      13.54925,
                      52.01648
                    ],
                    [
                      13.54994,
                      52.01581
                    ],
                    [
                      13.55078,
                      52.01486
                    ],
                    [
                      13.5515,
                      52.01392
                    ],
                    [
                      13.55253,
                      52.01239
                    ],
                    [
                      13.56289,
                      51.99654
                    ],
                    [
                      13.56327,
                      51.99588
                    ],
                    [
                      13.56382,
                      51.99489
                    ],
                    [
                      13.58605,
                      51.95254
                    ],
                    [
                      13.58812,
                      51.94854
                    ],
                    [
                      13.58865,
                      51.94742
                    ],
                    [
                      13.58898,
                      51.94654
                    ],
                    [
                      13.58925,
                      51.94566
                    ],
                    [
                      13.58934,
                      51.94526
                    ],
                    [
                      13.5895,
                      51.94438
                    ],
                    [
                      13.58957,
                      51.94373
                    ],
                    [
                      13.58961,
                      51.94262
                    ],
                    [
                      13.58956,
                      51.94177
                    ],
                    [
                      13.58949,
                      51.94125
                    ],
                    [
                      13.58932,
                      51.94035
                    ],
                    [
                      13.58902,
                      51.93929
                    ],
                    [
                      13.5792,
                      51.90884
                    ],
                    [
                      13.57847,
                      51.90653
                    ],
                    [
                      13.57833,
                      51.90594
                    ],
                    [
                      13.57816,
                      51.90488
                    ],
                    [
                      13.57811,
                      51.90425
                    ],
                    [
                      13.57809,
                      51.90362
                    ],
                    [
                      13.57814,
                      51.90265
                    ],
                    [
                      13.57821,
                      51.90201
                    ],
                    [
                      13.57833,
                      51.90135
                    ],
                    [
                      13.57848,
                      51.9007
                    ],
                    [
                      13.57866,
                      51.90008
                    ],
                    [
                      13.57894,
                      51.89932
                    ],
                    [
                      13.57925,
                      51.89859
                    ],
                    [
                      13.57956,
                      51.89799
                    ],
                    [
                      13.58001,
                      51.89722
                    ],
                    [
                      13.61337,
                      51.84291
                    ],
                    [
                      13.61425,
                      51.84152
                    ],
                    [
                      13.61489,
                      51.84066
                    ],
                    [
                      13.6155,
                      51.83994
                    ],
                    [
                      13.61605,
                      51.83936
                    ],
                    [
                      13.61665,
                      51.83877
                    ],
                    [
                      13.61743,
                      51.83807
                    ],
                    [
                      13.63071,
                      51.82673
                    ],
                    [
                      13.63161,
                      51.8259
                    ],
                    [
                      13.63229,
                      51.82517
                    ],
                    [
                      13.63274,
                      51.82457
                    ],
                    [
                      13.63307,
                      51.82406
                    ],
                    [
                      13.63333,
                      51.82355
                    ],
                    [
                      13.63356,
                      51.82299
                    ],
                    [
                      13.63372,
                      51.82247
                    ],
                    [
                      13.6338,
                      51.8221
                    ],
                    [
                      13.63387,
                      51.82159
                    ],
                    [
                      13.6339,
                      51.82117
                    ],
                    [
                      13.63385,
                      51.82038
                    ],
                    [
                      13.63372,
                      51.81965
                    ],
                    [
                      13.6335,
                      51.81897
                    ],
                    [
                      13.63321,
                      51.81833
                    ],
                    [
                      13.63305,
                      51.81804
                    ],
                    [
                      13.63278,
                      51.81761
                    ],
                    [
                      13.63241,
                      51.81709
                    ],
                    [
                      13.63197,
                      51.8166
                    ],
                    [
                      13.63166,
                      51.81628
                    ],
                    [
                      13.63076,
                      51.81548
                    ],
                    [
                      13.62819,
                      51.81348
                    ],
                    [
                      13.62742,
                      51.81286
                    ],
                    [
                      13.62706,
                      51.81254
                    ],
                    [
                      13.62652,
                      51.81202
                    ],
                    [
                      13.6262,
                      51.81168
                    ],
                    [
                      13.62581,
                      51.81123
                    ],
                    [
                      13.62536,
                      51.81061
                    ],
                    [
                      13.62516,
                      51.8103
                    ],
                    [
                      13.62487,
                      51.80972
                    ],
                    [
                      13.62472,
                      51.8094
                    ],
                    [
                      13.62459,
                      51.80905
                    ],
                    [
                      13.62441,
                      51.8084
                    ],
                    [
                      13.62432,
                      51.80784
                    ],
                    [
                      13.62429,
                      51.80749
                    ],
                    [
                      13.62428,
                      51.80709
                    ],
                    [
                      13.62434,
                      51.80621
                    ],
                    [
                      13.62537,
                      51.79971
                    ],
                    [
                      13.62549,
                      51.79853
                    ],
                    [
                      13.62549,
                      51.79758
                    ],
                    [
                      13.62542,
                      51.79673
                    ],
                    [
                      13.62528,
                      51.79584
                    ],
                    [
                      13.62511,
                      51.7951
                    ],
                    [
                      13.62468,
                      51.79376
                    ],
                    [
                      13.61587,
                      51.76923
                    ],
                    [
                      13.61559,
                      51.76838
                    ],
                    [
                      13.59513,
                      51.69763
                    ],
                    [
                      13.59482,
                      51.69664
                    ],
                    [
                      13.58499,
                      51.66814
                    ],
                    [
                      13.58442,
                      51.66654
                    ],
                    [
                      13.58436,
                      51.66631
                    ],
                    [
                      13.57666,
                      51.64403
                    ],
                    [
                      13.57638,
                      51.64332
                    ],
                    [
                      13.57607,
                      51.64267
                    ],
                    [
                      13.57586,
                      51.64227
                    ],
                    [
                      13.57533,
                      51.64137
                    ],
                    [
                      13.57499,
                      51.64088
                    ],
                    [
                      13.57413,
                      51.63974
                    ],
                    [
                      13.56807,
                      51.63206
                    ],
                    [
                      13.5676,
                      51.63139
                    ],
                    [
                      13.56718,
                      51.63068
                    ],
                    [
                      13.56675,
                      51.62978
                    ],
                    [
                      13.56659,
                      51.62937
                    ],
                    [
                      13.56624,
                      51.62831
                    ],
                    [
                      13.5659,
                      51.62715
                    ],
                    [
                      13.56426,
                      51.62085
                    ],
                    [
                      13.56411,
                      51.6203
                    ],
                    [
                      13.56314,
                      51.61654
                    ],
                    [
                      13.56288,
                      51.61528
                    ],
                    [
                      13.5628,
                      51.61451
                    ],
                    [
                      13.56277,
                      51.61402
                    ],
                    [
                      13.56279,
                      51.61291
                    ],
                    [
                      13.56288,
                      51.61212
                    ],
                    [
                      13.56309,
                      51.61099
                    ],
                    [
                      13.56366,
                      51.60907
                    ],
                    [
                      13.56751,
                      51.59669
                    ],
                    [
                      13.56852,
                      51.59321
                    ],
                    [
                      13.57332,
                      51.5765
                    ],
                    [
                      13.57352,
                      51.57568
                    ],
                    [
                      13.57366,
                      51.57484
                    ],
                    [
                      13.57373,
                      51.57417
                    ],
                    [
                      13.5759,
                      51.54606
                    ],
                    [
                      13.57601,
                      51.54428
                    ],
                    [
                      13.57603,
                      51.54238
                    ],
                    [
                      13.5762,
                      51.50925
                    ],
                    [
                      13.57629,
                      51.50427
                    ],
                    [
                      13.57627,
                      51.50343
                    ],
                    [
                      13.57624,
                      51.50306
                    ],
                    [
                      13.57619,
                      51.50262
                    ],
                    [
                      13.57601,
                      51.50182
                    ],
                    [
                      13.57577,
                      51.50112
                    ],
                    [
                      13.57553,
                      51.50058
                    ],
                    [
                      13.57522,
                      51.5
                    ],
                    [
                      13.57469,
                      51.4992
                    ],
                    [
                      13.57432,
                      51.49873
                    ],
                    [
                      13.57371,
                      51.49806
                    ],
                    [
                      13.57307,
                      51.49746
                    ],
                    [
                      13.57244,
                      51.49694
                    ],
                    [
                      13.57182,
                      51.49649
                    ],
                    [
                      13.57131,
                      51.49616
                    ],
                    [
                      13.57032,
                      51.49558
                    ],
                    [
                      13.56572,
                      51.49321
                    ],
                    [
                      13.56481,
                      51.49271
                    ],
                    [
                      13.56306,
                      51.49163
                    ],
                    [
                      13.55101,
                      51.48395
                    ],
                    [
                      13.5499,
                      51.48328
                    ],
                    [
                      13.54908,
                      51.48282
                    ],
                    [
                      13.54835,
                      51.48245
                    ],
                    [
                      13.54739,
                      51.48199
                    ],
                    [
                      13.54679,
                      51.48173
                    ],
                    [
                      13.54533,
                      51.48114
                    ],
                    [
                      13.54381,
                      51.4806
                    ],
                    [
                      13.54326,
                      51.48042
                    ],
                    [
                      13.53003,
                      51.47643
                    ],
                    [
                      13.52841,
                      51.47591
                    ],
                    [
                      13.5274,
                      51.47553
                    ],
                    [
                      13.52693,
                      51.47534
                    ],
                    [
                      13.52597,
                      51.47489
                    ],
                    [
                      13.52522,
                      51.4745
                    ],
                    [
                      13.52458,
                      51.47413
                    ],
                    [
                      13.52386,
                      51.47367
                    ],
                    [
                      13.5235,
                      51.47342
                    ],
                    [
                      13.52316,
                      51.47316
                    ],
                    [
                      13.52237,
                      51.4725
                    ],
                    [
                      13.52193,
                      51.47209
                    ],
                    [
                      13.52163,
                      51.47177
                    ],
                    [
                      13.5211,
                      51.47117
                    ],
                    [
                      13.52088,
                      51.47089
                    ],
                    [
                      13.52054,
                      51.47041
                    ],
                    [
                      13.52014,
                      51.46975
                    ],
                    [
                      13.51978,
                      51.46902
                    ],
                    [
                      13.51949,
                      51.4683
                    ],
                    [
                      13.51632,
                      51.45941
                    ],
                    [
                      13.516513,
                      51.460071
                    ]
                  ]
                },
                "properties": {
                  "statusId": 6440441
                }
              }
            ]
          }
        },
        "event": null,
        "userDetails": {
          "id": 2472066,
          "displayName": "Adri",
          "username": "Adriii666",
          "profilePicture": "https://traewelling.de/uploads/avatars/2472066_1764422222.png",
          "mastodonUrl": null,
          "preventIndex": false
        },
        "tags": [],
        "color": "#d1024e",
        "category": "regionalExp"
      }
    }
  ]
}